<?xml version="1.0"?>
<!DOCTYPE hibernate-mapping PUBLIC
    "-//Hibernate/Hibernate Mapping DTD 2.0//EN"
    "http://hibernate.sourceforge.net/hibernate-mapping-2.0.dtd" >
    
<hibernate-mapping>
<!-- 
    Created by the Middlegen Hibernate plugin 2.2

    http://boss.bekk.no/boss/middlegen/
    http://www.hibernate.org/
-->

<class 
    name="de.mbws.common.data.generated.Npc" 
    table="npc"
>

    <id
        name="id"
        type="java.lang.Long"
        column="id"
    >
		    <meta attribute="field-description" inherit="false">
		       auto_increment
		    </meta>
    
        <generator class="assigned" />
    </id>

    <property
        name="name"
        type="java.lang.String"
        column="name"
        not-null="true"
        length="255"
    />
    <property
        name="health"
        type="java.lang.Object"
        column="health"
        not-null="true"
        length="10"
    />
    <property
        name="mana"
        type="java.lang.Object"
        column="mana"
        not-null="true"
        length="10"
    />
    <property
        name="stamina"
        type="java.lang.Object"
        column="stamina"
        not-null="true"
        length="10"
    />
    <property
        name="age"
        type="java.lang.Object"
        column="age"
        not-null="true"
        length="10"
    />
    <property
        name="strength"
        type="java.lang.Object"
        column="strength"
        not-null="true"
        length="10"
    />
    <property
        name="intelligence"
        type="java.lang.Object"
        column="intelligence"
        not-null="true"
        length="10"
    />
    <property
        name="dexterity"
        type="java.lang.Object"
        column="dexterity"
        not-null="true"
        length="10"
    />
    <property
        name="constitution"
        type="java.lang.Object"
        column="constitution"
        not-null="true"
        length="10"
    />
    <property
        name="isspecial"
        type="byte"
        column="isspecial"
        not-null="true"
        length="1"
    />

    <!-- Associations -->
  
    <!-- bi-directional many-to-one association to Race -->
    <many-to-one
        name="race"
        class="de.mbws.common.data.generated.Race"
        not-null="true"
    >
        <column name="race_id" />
    </many-to-one>
    <!-- bi-directional one-to-one association to NpcStatus -->
    <one-to-one
        name="npcStatus"
        class="de.mbws.common.data.generated.NpcStatus"
        outer-join="auto"
    />
    <!-- bi-directional one-to-many association to NpcWorldobjectMapping -->

    <set
        name="npcWorldobjectMappings"
        lazy="true"
        inverse="true"
		cascade="none"

    >
        <key>
            <column name="npc_id" />
        </key>
        
        <one-to-many 
            class="de.mbws.common.data.generated.NpcWorldobjectMapping"
        />
    </set>
    <!-- bi-directional one-to-many association to NpcSkillMapping -->

    <set
        name="npcSkillMappings"
        lazy="true"
        inverse="true"
		cascade="none"

    >
        <key>
            <column name="npc_id" />
        </key>
        
        <one-to-many 
            class="de.mbws.common.data.generated.NpcSkillMapping"
        />
    </set>

</class>
</hibernate-mapping>
